[
	{
		"buy_sell_id": "1828582"
	},
	{
		"buy_sell_id": "2398816"
	},
	{
		"buy_sell_id": "9899009"
	},
	{
		"buy_sell_id": "9966064"
	},
	{
		"buy_sell_id": "9968637"
	},
	{
		"buy_sell_id": "9968639"
	},
	{
		"buy_sell_id": "9968657"
	},
	{
		"buy_sell_id": "9968659"
	},
	{
		"buy_sell_id": "9971665"
	},
	{
		"buy_sell_id": "9971667"
	},
	{
		"buy_sell_id": "9971669"
	},
	{
		"buy_sell_id": "9971675"
	},
	{
		"buy_sell_id": "9971677"
	},
	{
		"buy_sell_id": "9971856"
	},
	{
		"buy_sell_id": "9971858"
	},
	{
		"buy_sell_id": "9971860"
	},
	{
		"buy_sell_id": "9971862"
	},
	{
		"buy_sell_id": "9971864"
	},
	{
		"buy_sell_id": "9971869"
	},
	{
		"buy_sell_id": "9971871"
	},
	{
		"buy_sell_id": "9971873"
	},
	{
		"buy_sell_id": "9971875"
	},
	{
		"buy_sell_id": "9972851"
	},
	{
		"buy_sell_id": "9972853"
	},
	{
		"buy_sell_id": "9972860"
	}
]